{
  "entrypoints": [
    "main"
  ],
  "origins": {
    "1": [
      0,
      2,
      4,
      11,
      15,
      16,
      1
    ],
    "2": [
      0,
      1,
      11,
      15,
      16,
      2
    ],
    "styles": [
      1,
      2,
      4,
      11,
      13,
      14,
      15,
      16,
      0
    ],
    "@site/docs/snippets/git.md": [
      3
    ],
    "@theme/DocItem": [
      0,
      1,
      4
    ],
    "@site/docs/020.tool.md": [
      5
    ],
    "@site/docs/010.research.md": [
      6
    ],
    "@site/docs/snippets/java.md": [
      7
    ],
    "@site/docs/snippets/docker.md": [
      8
    ],
    "~docs/default/version-current-metadata-prop-751.json": [
      9
    ],
    "@site/docs/snippets/nodejs.md": [
      10
    ],
    "@site/src/pages/index.js": [
      0,
      1,
      2,
      11
    ],
    "@site/docs/000.index.md": [
      12
    ],
    "@generated/docusaurus.config": [
      0,
      14,
      13
    ],
    "main": [
      0,
      14,
      13
    ],
    "runtime~main": [
      0,
      13,
      14
    ],
    "@theme/DocPage": [
      0,
      1,
      2,
      16
    ],
    "@theme/NotFound": [
      0,
      1,
      2,
      16
    ]
  },
  "assets": {
    "0": {
      "css": [
        {
          "file": "styles.21f0090d.css",
          "hash": "51000475f92f78db187e",
          "publicPath": "/styles.21f0090d.css"
        }
      ],
      "js": [
        {
          "file": "styles.bfbc9b35.js",
          "hash": "51000475f92f78db187e",
          "publicPath": "/styles.bfbc9b35.js"
        }
      ]
    },
    "1": {
      "js": [
        {
          "file": "1.7991fe4a.js",
          "hash": "ae98acc52c5bcc6f3a64",
          "publicPath": "/1.7991fe4a.js"
        }
      ]
    },
    "2": {
      "js": [
        {
          "file": "2.8f665afd.js",
          "hash": "b8578f848a2eb8d9f02b",
          "publicPath": "/2.8f665afd.js"
        }
      ]
    },
    "3": {
      "js": [
        {
          "file": "0bc45167.e221d961.js",
          "hash": "f5473afbfe6946ec9c99",
          "publicPath": "/0bc45167.e221d961.js"
        }
      ]
    },
    "4": {
      "js": [
        {
          "file": "17896441.13267986.js",
          "hash": "059ee97f44da510a92c2",
          "publicPath": "/17896441.13267986.js"
        }
      ]
    },
    "5": {
      "js": [
        {
          "file": "370fa3f8.8adea844.js",
          "hash": "d5f7cdd50f342f67fb5a",
          "publicPath": "/370fa3f8.8adea844.js"
        }
      ]
    },
    "6": {
      "js": [
        {
          "file": "5bd3f688.644cf59a.js",
          "hash": "643287cea64aa69b2340",
          "publicPath": "/5bd3f688.644cf59a.js"
        }
      ]
    },
    "7": {
      "js": [
        {
          "file": "755855e2.8eaabf70.js",
          "hash": "e98a35a25d9451c1b6ea",
          "publicPath": "/755855e2.8eaabf70.js"
        }
      ]
    },
    "8": {
      "js": [
        {
          "file": "86c2bb54.afcd1b7e.js",
          "hash": "b963eba8c82c9751c1dc",
          "publicPath": "/86c2bb54.afcd1b7e.js"
        }
      ]
    },
    "9": {
      "js": [
        {
          "file": "935f2afb.33994af8.js",
          "hash": "a0c51c5b549a68ab781c",
          "publicPath": "/935f2afb.33994af8.js"
        }
      ]
    },
    "10": {
      "js": [
        {
          "file": "9c2fe012.8d878125.js",
          "hash": "271d60c9b8962834319b",
          "publicPath": "/9c2fe012.8d878125.js"
        }
      ]
    },
    "11": {
      "js": [
        {
          "file": "c4f5d8e4.7eee6051.js",
          "hash": "4422bca51cdc7a40f104",
          "publicPath": "/c4f5d8e4.7eee6051.js"
        }
      ]
    },
    "12": {
      "js": [
        {
          "file": "fe1bac53.bd27ab0b.js",
          "hash": "e23a1835a8de85337d2f",
          "publicPath": "/fe1bac53.bd27ab0b.js"
        }
      ]
    },
    "13": {
      "js": [
        {
          "file": "main.020c1944.js",
          "hash": "6e615daf510af4fc96af",
          "publicPath": "/main.020c1944.js"
        }
      ]
    },
    "14": {
      "js": [
        {
          "file": "runtime~main.858611c1.js",
          "hash": "4f6457916c4c015c750b",
          "publicPath": "/runtime~main.858611c1.js"
        }
      ]
    },
    "16": {
      "js": [
        {
          "file": "15.8873c96f.js",
          "hash": "2ddf9d48fea2d9fbaab1",
          "publicPath": "/15.8873c96f.js"
        },
        {
          "file": "16.1e009402.js",
          "hash": "021ca7ae932007e60885",
          "publicPath": "/16.1e009402.js"
        }
      ]
    }
  }
}